pup.py
setup.py
Puppy.egg-info/PKG-INFO
Puppy.egg-info/SOURCES.txt
Puppy.egg-info/dependency_links.txt
Puppy.egg-info/requires.txt
Puppy.egg-info/top_level.txt
Puppy.egg-info/zip-safe