Metadata-Version: 1.1
Name: Puppy
Version: 0.1.7
Summary: DSL for creating NetCDF files
Home-page: http://bitbucket.org/robertodealmeida/puppy/
Author: Roberto De Almeida
Author-email: roberto@dealmeida.net
License: MIT
Keywords: netcdf data array math
Platform: UNKNOWN
Classifier: Development Status :: 5 - Production/Stable
Classifier: Environment :: Console
Classifier: Intended Audience :: Developers
Classifier: Intended Audience :: Science/Research
Classifier: License :: OSI Approved :: MIT License
Classifier: Operating System :: OS Independent
Classifier: Programming Language :: Python
Classifier: Topic :: Scientific/Engineering
Classifier: Topic :: Software Development :: Libraries :: Python Modules
